source/digit_decoder.sv
module digit_decoder(
    input logic clk, nrst,
    input logic keystrobe,
    input logic [3:0] keycode,
    output logic isdig,
    output logic [3:0] digitCode
 );
    logic [3:0] next_digitCode; // Intermediate Signal

    // Use a flip flop to remember the  current value inputed
    always_ff @(posedge clk, negedge nrst) begin
        if(0 == nrst) begin
            digitCode <= 0;
        end
        else begin
            digitCode <= next_digitCode;
        end 
    end
    always_comb begin
        if(keystrobe && keycode < 4'b1010 && nrst == 1) begin
            next_digitCode = keycode;
            isdig = 1;
        end
        else begin
            next_digitCode = 4'b0000;
            isdig = 0;
        end
    end
endmodule

source/tb_digit_decoder.sv
`timescale 1ns/10ps

module tb_key_encoder();
    localparam CLK_PERIOD =100;
    // Declare Test Case Signals
    integer tb_test_num;
    string tb_test_case;
    logic tb_mismatch;
    logic tb_check;

    // Declare DUT Connection Signals
    logic tb_clk;
    logic tb_nrst;
    logic tb_keystrobe;
    logic [3:0] tb_keycode;
    logic tb_isdig;
    logic [3:0] tb_digitCode;

    // Declare the Test Bench Signals for Expected Results
    logic tb_isdig_expected;
    logic [3:0] tb_digitCode_expected;

    task reset_dut;
    begin
        //Activate the reset
        tb_nrst = 1'b0;
        @(posedge tb_clk);
        @(posedge tb_clk);

        //Wait until safely away from rising edge of the clk
        @(negedge tb_clk);
        tb_nrst = 1'b1;

        // Leave out of reset for a couple cycles before allowing other
        // Wait for negative clock edges,
        // since inputs to DUT should normally be applied away from rising edge
        @(negedge tb_clk);
        @(negedge tb_clk);
    end
    endtask
    task check_output_keycode;
        input string check_tag;
    begin
        tb_check = 1'b1;
        tb_mismatch = 1'b0;
        if(tb_digitCode_expected == tb_digitCode) begin
            $display("Correct code output %swhen tested. This case is called %s", tb_check, check_tag);
        end
        else begin
            $error("Incorrect code output %swhen tested. This case is called %s", tb_mismatch, check_tag);
        end
    end
    endtask

    task check_output_isdig;
        input string check_tag;
    begin
        tb_check = 1'b1;
        tb_mismatch = 1'b0;
        if(tb_isdig_expected == tb_isdig) begin
            $display("Correct strobe utput %s when tested. This case is called %s", tb_check, check_tag);
        end
        else begin
            $error("Incorrect strobe output %s when tested. Thus case is called %s", tb_mismatch, check_tag);
        end
    end
    endtask

    task inactivate_signals;
    begin
        tb_keycode = 4'b0;
        tb_isdig_expected = 0;
        tb_digitCode_expected = 4'b0;
    end
    endtask

always begin
    tb_clk = 1'b0;
    #(CLK_PERIOD/2.0);
    tb_clk = 1'b1;
    #(CLK_PERIOD/2.0);
end
    digit_decoder DUT
    (
        .clk(tb_clk),
        .nrst(tb_nrst),
        .keystrobe(tb_keystrobe),
        .keycode(tb_keycode),
        .isdig(tb_isdig),
        .digitCode(tb_digitCode)
    );

    initial begin
        $dumpfile ("dump.vcd");
        $dumpvars;
    end

    initial begin
        #(0.1);
        reset_dut();
        inactivate_signals();
        tb_test_num = tb_test_num + 1;
        tb_nrst = 0;
        tb_keystrobe = 1;
        tb_keycode = 4'b1001;
        tb_digitCode_expected = 4'b0000;
        tb_isdig_expected = 0;
        @(posedge tb_clk);
        @(negedge tb_clk);
        check_output_keycode("power on RESET.");
        check_output_isdig("power on RESET.");

        #(0.1);
        reset_dut();
        inactivate_signals();
        tb_test_num = tb_test_num + 1;
        tb_keystrobe = 0;
        tb_keycode = 4'b1010;
        tb_digitCode_expected = 4'b0000;
        tb_isdig_expected = 0;
        @(posedge tb_clk);
        @(negedge tb_clk);
        check_output_keycode("strobe 0 and keyinput 10.");
        check_output_isdig("strobe 0 and keyinput 10.");

        #(0.1);
        reset_dut();
        inactivate_signals();
        tb_test_num = tb_test_num + 1;
        tb_keystrobe = 0;
        tb_keycode = 4'b0011;
        tb_digitCode_expected = 4'b0000;
        tb_isdig_expected = 0;
        @(posedge tb_clk);
        @(negedge tb_clk);
        check_output_keycode("strobe 0 and keyinput 3.");
        check_output_isdig("strobe 0 and keyinput 3.");

        #(0.1);
        reset_dut();
        inactivate_signals();
        tb_test_num = tb_test_num + 1;
        tb_keystrobe = 0;
        tb_keycode = 4'b1001;
        tb_digitCode_expected = 4'b0000;
        tb_isdig_expected = 0;
        @(posedge tb_clk);
        @(negedge tb_clk);
        check_output_keycode("strobe 0 and keyinput 9.");
        check_output_isdig("strobe 0 and keyinput 9.");

        #(0.1);
        reset_dut();
        inactivate_signals();
        tb_test_num = tb_test_num + 1;
        tb_keystrobe = 0;
        tb_keycode = 4'b0111;
        tb_digitCode_expected = 4'b0000;
        tb_isdig_expected = 0;
        @(posedge tb_clk);
        @(negedge tb_clk);
        check_output_keycode("strobe 0 and keyinput 7.");
        check_output_isdig("strobe 0 and keyinput 7.");

        #(0.1);
        reset_dut();
        inactivate_signals();
        tb_test_num = tb_test_num + 1;
        tb_keystrobe = 0;
        tb_keycode = 4'b1011;
        tb_digitCode_expected = 4'b0000;
        tb_isdig_expected = 0;
        @(posedge tb_clk);
        @(negedge tb_clk);
        check_output_keycode("strobe 0 and keyinput 11.");
        check_output_isdig("strobe 0 and keyinput 11.");

        #(0.1);
        reset_dut();
        inactivate_signals();
        tb_test_num = tb_test_num + 1;
        tb_keystrobe = 1;
        tb_keycode = 4'b1001;
        tb_digitCode_expected = 4'b1001;
        tb_isdig_expected = 1;
        @(posedge tb_clk);
        @(negedge tb_clk);
        check_output_keycode("strobe 1 and keyinput 9.");
        check_output_isdig("strobe 1 and keyinput 9.");

        #(0.1);
        reset_dut();
        inactivate_signals();
        tb_test_num = tb_test_num + 1;
        tb_keystrobe = 1;
        tb_keycode = 4'b1010;
        tb_digitCode_expected = 4'b0000;
        tb_isdig_expected = 0;
        @(posedge tb_clk);
        @(negedge tb_clk);
        check_output_keycode("strobe 1 and keyinput 10.");
        check_output_isdig("strobe 1 and keyinput 10.");

        #(0.1);
        reset_dut();
        inactivate_signals();
        tb_test_num = tb_test_num + 1;
        tb_keystrobe = 1;
        tb_keycode = 4'b1100;
        tb_digitCode_expected = 4'b0000;
        tb_isdig_expected = 0;
        @(posedge tb_clk);
        @(negedge tb_clk);
        check_output_keycode("strobe 1 and keyinput 12.");
        check_output_isdig("strobe 1 and keyinput 12.");

        #(0.1);
        reset_dut();
        inactivate_signals();
        tb_test_num = tb_test_num + 1;
        tb_keystrobe = 1;
        tb_keycode = 4'b0001;
        tb_digitCode_expected = 4'b0001;
        tb_isdig_expected = 1;
        @(posedge tb_clk);
        @(negedge tb_clk);
        check_output_keycode("strobe 1 and keyinput 1.");
        check_output_isdig("strobe 1 and keyinput 1.");

        #(0.1);
        reset_dut();
        inactivate_signals();
        tb_test_num = tb_test_num + 1;
        tb_keystrobe = 1;
        tb_keycode = 4'b0010;
        tb_digitCode_expected = 4'b0010;
        tb_isdig_expected = 1;
        @(posedge tb_clk);
        @(negedge tb_clk);
        check_output_keycode("strobe 1 and keyinput 2.");
        check_output_isdig("strobe 1 and keyinput 2.");

        #(0.1);
        reset_dut();
        inactivate_signals();
        tb_test_num = tb_test_num + 1;
        tb_keystrobe = 1;
        tb_keycode = 4'b1000;
        tb_digitCode_expected = 4'b1000;
        tb_isdig_expected = 1;
        @(posedge tb_clk);
        @(negedge tb_clk);
        check_output_keycode("strobe 1 and keyinput 8.");
        check_output_isdig("strobe 1 and keyinput 8.");

    $finish;
    end
endmodule

dump.vcd
$date
	Mon Jun 26 09:27:27 2023
$end
$version
	Icarus Verilog
$end
$timescale
	10ps
$end
$scope module tb_key_encoder $end
$var wire 1 ! tb_isdig $end
$var wire 4 " tb_digitCode [3:0] $end
$var parameter 32 # CLK_PERIOD $end
$var reg 1 $ tb_check $end
$var reg 1 % tb_clk $end
$var reg 4 & tb_digitCode_expected [3:0] $end
$var reg 1 ' tb_isdig_expected $end
$var reg 4 ( tb_keycode [3:0] $end
$var reg 1 ) tb_keystrobe $end
$var reg 1 * tb_mismatch $end
$var reg 1 + tb_nrst $end
$var integer 32 , tb_test_num [31:0] $end
$scope module DUT $end
$var wire 1 % clk $end
$var wire 4 - keycode [3:0] $end
$var wire 1 ) keystrobe $end
$var wire 1 + nrst $end
$var reg 4 . digitCode [3:0] $end
$var reg 1 ! isdig $end
$var reg 4 / next_digitCode [3:0] $end
$upscope $end
$scope task check_output_isdig $end
$upscope $end
$scope task check_output_keycode $end
$upscope $end
$scope task inactivate_signals $end
$upscope $end
$scope task reset_dut $end
$upscope $end
$upscope $end
$enddefinitions $end
$comment Show the parameter values. $end
$dumpall
b1100100 #
$end
#0
$dumpvars
b0 /
bx .
bx -
bx ,
x+
x*
x)
bx (
x'
bx &
0%
x$
bx "
0!
$end
#10
b0 "
b0 .
0+
#5000
1%
#10000
0%
#15000
1%
#20000
1+
0%
#25000
1%
#30000
0%
#35000
1%
#40000
1)
0+
b0 &
0'
b1001 (
b1001 -
0%
#45000
1%
#50000
0*
1$
0%
#55000
1%
#60000
0%
#65000
1%
#70000
1!
b1001 /
1+
0%
#75000
b1001 "
b1001 .
1%
#80000
0%
#85000
1%
#90000
0!
b0 /
0)
b1010 (
b1010 -
0%
#95000
b0 "
b0 .
1%
#100000
0%
#100010
0+
#105000
1%
#110000
0%
#115000
1%
#120000
1+
0%
#125000
1%
#130000
0%
#135000
1%
#140000
b11 (
b11 -
0%
#145000
1%
#150000
0%
#150010
0+
#155000
1%
#160000
0%
#165000
1%
#170000
1+
0%
#175000
1%
#180000
0%
#185000
1%
#190000
b1001 (
b1001 -
0%
#195000
1%
#200000
0%
#200010
0+
#205000
1%
#210000
0%
#215000
1%
#220000
1+
0%
#225000
1%
#230000
0%
#235000
1%
#240000
b111 (
b111 -
0%
#245000
1%
#250000
0%
#250010
0+
#255000
1%
#260000
0%
#265000
1%
#270000
1+
0%
#275000
1%
#280000
0%
#285000
1%
#290000
b1011 (
b1011 -
0%
#295000
1%
#300000
0%
#300010
0+
#305000
1%
#310000
0%
#315000
1%
#320000
1+
0%
#325000
1%
#330000
0%
#335000
1%
#340000
1!
b1001 /
1'
b1001 &
1)
b1001 (
b1001 -
0%
#345000
b1001 "
b1001 .
1%
#350000
0%
#350010
b0 "
b0 .
0!
b0 /
0+
#355000
1%
#360000
0%
#365000
1%
#370000
1!
b1001 /
1+
0%
#375000
b1001 "
b1001 .
1%
#380000
0%
#385000
1%
#390000
0!
b0 /
b0 &
0'
b1010 (
b1010 -
0%
#395000
b0 "
b0 .
1%
#400000
0%
#400010
0+
#405000
1%
#410000
0%
#415000
1%
#420000
1+
0%
#425000
1%
#430000
0%
#435000
1%
#440000
b1100 (
b1100 -
0%
#445000
1%
#450000
0%
#450010
0+
#455000
1%
#460000
0%
#465000
1%
#470000
1+
0%
#475000
1%
#480000
0%
#485000
1%
#490000
1!
b1 /
1'
b1 &
b1 (
b1 -
0%
#495000
b1 "
b1 .
1%
#500000
0%
#500010
b0 "
b0 .
0!
b0 /
0+
#505000
1%
#510000
0%
#515000
1%
#520000
1!
b1 /
1+
0%
#525000
b1 "
b1 .
1%
#530000
0%
#535000
1%
#540000
b10 /
b10 &
1'
b10 (
b10 -
0%
#545000
b10 "
b10 .
1%
#550000
0%
#550010
b0 "
b0 .
0!
b0 /
0+
#555000
1%
#560000
0%
#565000
1%
#570000
1!
b10 /
1+
0%
#575000
b10 "
b10 .
1%
#580000
0%
#585000
1%
#590000
b1000 /
b1000 &
1'
b1000 (
b1000 -
0%
#595000
b1000 "
b1000 .
1%
