source/key_encoder_binary.sv
module key_encoder_binary(
    input logic clk, nrst, 
    input logic [1:0]keypad,
    output logic [3:0] keycode,
    output logic move_on
);

    // Declare Internal Signals
    logic [1:0] keypad_async, keypad_sync, keypad_i; 
    logic strobe, next_move_on,code_choice, use_code;
    logic [3:0] state, next_state, partial_code, next_partial_code, keycode_next;
    typedef enum logic [3:0] {s0, s1, s2, s3, s4, s5} digit_state;

    // Flip Flops to syncronize, detect edge, and keep keycode
    always_ff @(posedge clk, negedge nrst) begin
        if(nrst == 0) begin
            keypad_async <= 2'b0;
            keypad_sync  <= 2'b0;
            keypad_i     <= 2'b0;
            state        <= s0;
            keycode      <= 4'b0;
        end
        else begin
            keypad_async <= keypad;
            keypad_sync  <= keypad_async;
            keypad_i     <= keypad_sync;
            state        <= next_state;
            keycode      <= partial_code;
    end
    end

    // Edge detector logic. This detects a rising edge
    always_comb begin
        if((|keypad_sync) && ~(|keypad_i)) begin
            strobe = 1'b1;
        end
        else begin
            strobe = 1'b0;
        end
    end

    // FSM logic. It only moves forward if a strobe is detected
    always_comb begin
        next_state = state;
        case(state)
            s0: begin
                if(strobe) begin
                    next_state = s1;
                end
                else begin
                    next_state = s0;
                end
            end
            s1: begin
                if(strobe) begin
                    next_state = s2;
                end
                else begin
                    next_state = s1;
                end
            end
            s2: begin
                if(strobe) begin
                    next_state = s3;
                end
                else begin
                    next_state = s2;
                end
            end
            s3: begin
                if(strobe) begin
                    next_state = s4;
                end
                else begin
                    next_state = s3;
                end
            end
            s4: begin
                if(move_on) begin
                    next_state = s0;
                end
                else begin
                    next_state = s4;
                end
            end
            
            default: begin
                next_state = state;
            end
        endcase
    end  
    always_comb begin
        case(state)
            s0: move_on = 1'b0;
            s1: move_on = 1'b0;
            s2: move_on = 1'b0;
            s3: move_on = 1'b0;
            s4: move_on = 1'b1;
            default: move_on = 1'b0;
        endcase
    end
    //Shift register logic. It shifts each input to create the code
    always_comb begin
        partial_code = keycode;
        if(state == s0 && use_code && strobe) begin
            partial_code = {keycode[2:0], code_choice};
        end
        else if(state == s1 && use_code && strobe) begin
            partial_code = {keycode[2:0], code_choice};
        end
        else if(state == s2 && use_code && strobe) begin
            partial_code = {keycode[2:0], code_choice};
        end
        else if(state == s3 && use_code && strobe) begin
            partial_code = {keycode[2:0], code_choice};
        end
        else if(state == s4 && use_code && strobe) begin
            partial_code = {keycode[2:0], code_choice};
        end
    end

    // Assiges a value to the keycode
    always_comb begin
        if(strobe) begin
            case(keypad_sync)
                2'b01: begin
                    code_choice = 1'b0;
                    use_code = 1'b1;
                end
                2'b10: begin
                    code_choice = 1'b1;
                    use_code = 1'b1;
                end
                default: begin
                    code_choice = 1'b0;
                    use_code = 1'b0;
                end
            endcase
        end
        else begin
            code_choice = 1'b0;
            use_code = 1'b0;
        end
    end
endmodule

source/tb_key_encoder_binary.sv
`timescale 1ns/10ps

module tb_key_encoder_binary();
    localparam CLK_PERIOD = 100;
    // Declare Test Case Signals
    integer tb_test_num;
    string tb_test_case;
    logic tb_mismatch;
    logic tb_check;

    // Declare DUT Connection Signals
    logic tb_clk;
    logic tb_nrst;
    logic [1:0] tb_keypad;
    logic tb_move_on;
    logic [3:0] tb_keycode;

    // Declare the Test Bench Signals for Expected Results
    logic tb_isdig_expected;
    logic [3:0] tb_keycode_expected;
    logic tb_move_on_expected;

    task reset_dut();
    begin
        tb_nrst = 1'b0;
        @(posedge tb_clk);
        @(posedge tb_clk);

        // Wait until safely away from rising edge of clk
        @(negedge tb_clk);
        tb_nrst = 1'b1;
        @(negedge tb_clk);
        @(negedge tb_clk);
    end
    endtask

    task check_output_keycode;
        input string check_tag;
    begin
        tb_check = 1'b1;
        tb_mismatch = 1'b0;
        if(tb_keycode_expected == tb_keycode) begin
            $display("Correct code output %swhen tested. Ths case is called %s", tb_check, check_tag);
        end
        else begin
            $error("Incorrect code output %swhen tested. This case is called %s", tb_mismatch, check_tag);
        end
    end
    endtask

    task check_output_move_on;
        input string check_tag;
    begin
        tb_check = 1'b1;
        tb_mismatch = 1'b0;
        if(tb_move_on_expected == tb_move_on) begin
            $display("Correct strobe output %swhen tested. This case is called %s", tb_check, check_tag);
        end
        else begin
            $error("Incorrect strobe output %swhen tested. This case is called %s", tb_mismatch, check_tag);
        end
    end
    endtask

    task inactivate_signals;
    begin
        tb_keypad = 2'b0;

        tb_move_on_expected = 0;
        tb_keycode_expected = 4'b0;
    end
    endtask

    always begin
        tb_clk = 1'b0;
        #(CLK_PERIOD/2.0);
        tb_clk = 1'b1;
        #(CLK_PERIOD/2.0);
    end

    key_encoder_binary DUT
    (
        .clk(tb_clk),
        .nrst(tb_nrst),
        .keypad(tb_keypad),
        .keycode(tb_keycode),
        .move_on(tb_move_on)
    );

    initial begin
        $dumpfile ("dump.vcd");
        $dumpvars;
    end

    initial begin
        #(0.1)
        tb_nrst = 1;
        tb_keypad = 2'b00;
        #(0.1)
        reset_dut();
        inactivate_signals();
        tb_test_num = tb_test_num + 1;
        tb_nrst = 1;
        tb_keypad = 2'b10;
        tb_keycode_expected = 4'b0001;
        tb_move_on_expected = 0;
        @(posedge tb_clk);
        @(posedge tb_clk);
        @(posedge tb_clk);
        @(negedge tb_clk);

        // tb_keypad = 2'b01;
        // tb_keycode_expected = 4'b0010;
        // tb_move_on_expected = 0;
        // @(posedge tb_clk);
        // @(posedge tb_clk);
        // @(negedge tb_clk);
        check_output_keycode("state 1");
        check_output_move_on("state 1");

        $finish;
    end
endmodule

dump.vcd
$date
	Tue Jun 27 14:50:21 2023
$end
$version
	Icarus Verilog
$end
$timescale
	10ps
$end
$scope module tb_key_encoder_binary $end
$var wire 1 ! tb_move_on $end
$var wire 4 " tb_keycode [3:0] $end
$var parameter 32 # CLK_PERIOD $end
$var reg 1 $ tb_check $end
$var reg 1 % tb_clk $end
$var reg 4 & tb_keycode_expected [3:0] $end
$var reg 2 ' tb_keypad [1:0] $end
$var reg 1 ( tb_mismatch $end
$var reg 1 ) tb_move_on_expected $end
$var reg 1 * tb_nrst $end
$var integer 32 + tb_test_num [31:0] $end
$scope module DUT $end
$var wire 1 % clk $end
$var wire 2 , keypad [1:0] $end
$var wire 1 * nrst $end
$var reg 1 - code_choice $end
$var reg 4 . keycode [3:0] $end
$var reg 2 / keypad_async [1:0] $end
$var reg 2 0 keypad_i [1:0] $end
$var reg 2 1 keypad_sync [1:0] $end
$var reg 1 ! move_on $end
$var reg 4 2 next_state [3:0] $end
$var reg 4 3 partial_code [3:0] $end
$var reg 4 4 state [3:0] $end
$var reg 1 5 strobe $end
$var reg 1 6 use_code $end
$upscope $end
$scope task check_output_keycode $end
$upscope $end
$scope task check_output_move_on $end
$upscope $end
$scope task inactivate_signals $end
$upscope $end
$scope task reset_dut $end
$upscope $end
$upscope $end
$enddefinitions $end
$comment Show the parameter values. $end
$dumpall
b1100100 #
$end
#0
$dumpvars
06
05
bx 4
bx 3
bx 2
bx 1
bx 0
bx /
bx .
0-
bx ,
bx +
x*
x)
x(
bx '
bx &
0%
x$
bx "
0!
$end
#10
b0 '
b0 ,
1*
#20
b0 3
b0 2
b0 "
b0 .
b0 4
b0 0
b0 1
b0 /
0*
#5000
1%
#10000
0%
#15000
1%
#20000
1*
0%
#25000
1%
#30000
0%
#35000
1%
#40000
b10 '
b10 ,
b1 &
0)
0%
#45000
b10 /
1%
#50000
0%
#55000
b1 3
b1 2
16
1-
15
b10 1
1%
#60000
0%
#65000
06
0-
05
b1 "
b1 .
b1 4
b10 0
1%
#70000
0(
1$
0%
